library/__init__.py
library/pycal.py
simple_pycal-0.0.1.dist-info/METADATA
simple_pycal-0.0.1.dist-info/WHEEL
simple_pycal-0.0.1.dist-info/top_level.txt
simple_pycal-0.0.1.dist-info/RECORD
